bactax/__init__.py
bactax/errors.py
bactax/gram.py
bactax/ncbi.py
bactax/tax.py
bactax/taxonomy_2025-05-09.csv.gz
bactax/utils.py
bactax-0.2.0.dist-info/LICENSE
bactax-0.2.0.dist-info/METADATA
bactax-0.2.0.dist-info/WHEEL
bactax-0.2.0.dist-info/RECORD
