Metadata-Version: 2.1
Name: bactax
Version: 0.2.0
Summary: A simple python tool for getting bacterial taxonomy and gram stain information from NCBI taxonomy data.
License: MIT
Author: Adam Bates
Author-email: adambates923@gmail.com
Requires-Python: >=3.9,<4.0
Classifier: License :: OSI Approved :: MIT License
Classifier: Programming Language :: Python :: 3
Classifier: Programming Language :: Python :: 3.9
Classifier: Programming Language :: Python :: 3.10
Classifier: Programming Language :: Python :: 3.11
Classifier: Programming Language :: Python :: 3.12
Requires-Dist: polars (>=1.19.0,<2.0.0)
Requires-Dist: requests (>=2.32.3,<3.0.0)
Requires-Dist: rich (>=13.9.4,<14.0.0)
